vault_secret_manager/__init__.py
vault_secret_manager/__main__.py
vault_secret_manager/main.py
vault_secret_manager-1.0.0.dist-info/METADATA
vault_secret_manager-1.0.0.dist-info/WHEEL
vault_secret_manager-1.0.0.dist-info/entry_points.txt
vault_secret_manager-1.0.0.dist-info/RECORD
